README.md
setup.py
openapi_data_generator/InvalidObjectGenerator.py
openapi_data_generator/ObjectGenerator.py
openapi_data_generator/OpenApiDataGenerator.py
openapi_data_generator/OptionalCombinationGenerator.py
openapi_data_generator/__init__.py
openapi_data_generator.egg-info/PKG-INFO
openapi_data_generator.egg-info/SOURCES.txt
openapi_data_generator.egg-info/dependency_links.txt
openapi_data_generator.egg-info/requires.txt
openapi_data_generator.egg-info/top_level.txt
openapi_data_generator/utils/__init__.py
openapi_data_generator/utils/src/KeysHandler.py
openapi_data_generator/utils/src/LockDir.py
openapi_data_generator/utils/src/ObjectsHandler.py
openapi_data_generator/utils/src/SchemaHandler.py
openapi_data_generator/utils/src/__init__.py
openapi_data_generator/utils/test/__init__.py
openapi_data_generator/utils/test/test_ObjectHandler.py
openapi_data_generator/utils/test/test_SchemaHandler.py
test/__init__.py
test/test_ObjectGenerator.py
test/test_OpenApiDataGenerator.py
test/test_OptionalCombinationGenerator.py